drypy/__init__.py
drypy/patterns.py
drypy/test_utils.py
drypy/tests.py
drypy/utils.py
drypy-1.2.0.dist-info/LICENSE.txt
drypy-1.2.0.dist-info/METADATA
drypy-1.2.0.dist-info/WHEEL
drypy-1.2.0.dist-info/top_level.txt
drypy-1.2.0.dist-info/RECORD
