Metadata-Version: 2.1
Name: drypy
Version: 1.2.0
Summary: Python utilities to perform dryrun.
Home-page: https://github.com/dzanotelli/drypy
Author: Daniele Zanotelli
Author-email: dazano@gmail.com
License: MIT
Keywords: dryrun
Classifier: Development Status :: 5 - Production/Stable
Classifier: Intended Audience :: Developers
Classifier: Topic :: Software Development :: Build Tools
Classifier: License :: OSI Approved :: MIT License
Classifier: Operating System :: POSIX
Classifier: Programming Language :: Python :: 3
Requires-Python: >=3
License-File: LICENSE.txt
Provides-Extra: dev
